ansibilo/__init__.py
ansibilo/__main__.py
ansibilo/sphinxext.py
ansibilo/inventory/__init__.py
ansibilo/inventory/exporters.py
ansibilo/inventory/utils.py
ansibilo/modules/__init__.py
ansibilo/modules/facto.py
ansibilo/plugins/__init__.py
ansibilo/plugins/callbacks/__init__.py
ansibilo/plugins/callbacks/git_branch_uptodate.py
ansibilo/plugins/callbacks/pretty_print_result.py
ansibilo/plugins/callbacks/vaulted_slack.py
ansibilo/plugins/filters/__init__.py
ansibilo/plugins/filters/defaults.py
ansible/modules/ansibilo/__init__.py
ansible/modules/ansibilo/facto.py
ansible/plugins/callback/ansibilo/__init__.py
ansible/plugins/callback/ansibilo/git_branch_uptodate.py
ansible/plugins/callback/ansibilo/pretty_print_result.py
ansible/plugins/callback/ansibilo/vaulted_slack.py
ansible/plugins/filter/ansibilo/__init__.py
ansible/plugins/filter/ansibilo/defaults.py
ansibilo-0.5.dist-info/LICENSE
ansibilo-0.5.dist-info/METADATA
ansibilo-0.5.dist-info/WHEEL
ansibilo-0.5.dist-info/entry_points.txt
ansibilo-0.5.dist-info/top_level.txt
ansibilo-0.5.dist-info/RECORD
