Metadata-Version: 2.1
Name: ansibilo
Version: 0.5
Summary: Set of tools for Ansible
Home-page: https://github.com/Polyconseil/ansibilo/
Author: Polyconseil
Author-email: opensource+ansibilo@polyconseil.fr
License: BSD 3-Clause License
Keywords: ansible,tools
Platform: UNKNOWN
Classifier: Development Status :: 4 - Beta
Classifier: Environment :: Console
Classifier: Environment :: Plugins
Classifier: Intended Audience :: System Administrators
Classifier: License :: OSI Approved :: BSD License
Classifier: Programming Language :: Python
Classifier: Programming Language :: Python :: 2
Classifier: Programming Language :: Python :: 2.7
Classifier: Programming Language :: Python :: 3
Classifier: Programming Language :: Python :: 3.5
Classifier: Programming Language :: Python :: 3.6
Classifier: Topic :: System :: Systems Administration
Requires-Dist: ansible (>=2.4)
Requires-Dist: click
Requires-Dist: graphviz
Requires-Dist: humanize
Requires-Dist: netaddr
Requires-Dist: requests
Provides-Extra: sphinx
Requires-Dist: sphinx ; extra == 'sphinx'
